pixi_diff_to_markdown/__init__.py
pixi_diff_to_markdown/__main__.py
pixi_diff_to_markdown/cli.py
pixi_diff_to_markdown/diff.py
pixi_diff_to_markdown/environments_to_string.py
pixi_diff_to_markdown/markdown.py
pixi_diff_to_markdown/models.py
pixi_diff_to_markdown/pydantic_settings_extension.py
pixi_diff_to_markdown/settings.py
pixi_diff_to_markdown-0.3.7.dist-info/METADATA
pixi_diff_to_markdown-0.3.7.dist-info/WHEEL
pixi_diff_to_markdown-0.3.7.dist-info/entry_points.txt
pixi_diff_to_markdown-0.3.7.dist-info/licenses/LICENSE
pixi_diff_to_markdown-0.3.7.dist-info/RECORD
