Metadata-Version: 2.4
Name: pixi-diff-to-markdown
Version: 0.3.7
Summary: Tool for converting `pixi update` diffs to markdown
Project-URL: repository, https://github.com/pavelzw/pixi-diff-to-markdown
Author-email: Pavel Zwerschke <pavelzw@gmail.com>
License-File: LICENSE
Classifier: Programming Language :: Python :: 3
Classifier: Programming Language :: Python :: 3.14
Requires-Python: >=3.14
Requires-Dist: more-itertools<11,>=10.8.0
Requires-Dist: ordered-enum<0.0.11,>=0.0.10
Requires-Dist: py-rattler<0.17,>=0.16.0
Requires-Dist: pydantic-settings<3,>=2.11.0
Requires-Dist: pydantic<3,>=2.12.3
Requires-Dist: typer<0.21,>=0.20.0
